ping/__init__.py
ping/payment_links_api.py
ping/payments_api.py
ping/api_resources/__init__.py
ping/api_resources/payment_links_api/__init__.py
ping/api_resources/payment_links_api/invoice.py
ping/api_resources/payment_links_api/payment_links.py
ping/api_resources/payment_links_api/pings.py
ping/api_resources/payment_links_api/receipt.py
ping/api_resources/payments_api/__init__.py
ping/api_resources/payments_api/merchants.py
ping/api_resources/payments_api/paymentOrders.py
ping/api_resources/payments_api/payments.py
ping/api_resources/payments_api/payouts.py
ping/api_resources/payments_api/pings.py
ping/helper/__init__.py
ping/helper/apiHelper.py
ping/helper/apiResponse.py
tests/__init__.py
tests/test_helper.py
tests/payment_links_api/__init__.py
tests/payment_links_api/base_payment_links_api_test.py
tests/payment_links_api/test_invoice.py
tests/payment_links_api/test_payment_links.py
tests/payment_links_api/test_receipt.py
tests/payments_api/__init__.py
tests/payments_api/base_payments_api_test.py
tests/payments_api/test_merchant.py
tests/payments_api/test_payment.py
tests/payments_api/test_paymentOrder.py
ping_sdk-4.1.0.dist-info/LICENSE
ping_sdk-4.1.0.dist-info/METADATA
ping_sdk-4.1.0.dist-info/WHEEL
ping_sdk-4.1.0.dist-info/top_level.txt
ping_sdk-4.1.0.dist-info/RECORD
