Metadata-Version: 2.1
Name: ping-sdk
Version: 4.1.0
Summary: Use this Python library to manage Ping Payments API regarding merchants, payment orders, payments and payouts
Home-page: https://www.pingpayments.com/
Author: Ping Payments
Author-email: tech@pingpayments.com
License: MIT
Classifier: Intended Audience :: Developers
Classifier: License :: OSI Approved :: MIT License
Classifier: Operating System :: OS Independent
Classifier: Programming Language :: Python
Classifier: Programming Language :: Python :: 3.7
Classifier: Programming Language :: Python :: 3.8
Classifier: Programming Language :: Python :: 3.9
Classifier: Programming Language :: Python :: 3.10
Classifier: Programming Language :: Python :: Implementation :: PyPy
Classifier: Topic :: Software Development :: Libraries :: Python Modules
License-File: LICENSE
Requires-Dist: jsonpickle (>=1.4.1,~=1.4)
Requires-Dist: requests (~=2.25)
Requires-Dist: python-dotenv (~=0.20.0)
Requires-Dist: faker (~=14.2.0)
